{"schemaVersion":2,"gracePeriod":"72h","campaigns":[{"version":1,"advertiserId":"c46b4aba-1178-49ef-b2c8-b60a14d0871f","campaignId":"3438a452-0381-4e9f-8742-ac98d16fef9c","startAt":"2025-12-18T05:00:00.000Z","endAt":"2025-12-19T04:59:00.000Z","dailyCap":20,"priority":51,"ptr":1,"metrics":"confirmation","geoTargets":["AD","AE","AF","AL","AM","AO","AR","AT","AU","AW","AZ","BA","BB","BD","BE","BF","BG","BH","BI","BJ","BM","BN","BO","BR","BS","BT","BW","BZ","CA","CD","CG","CH","CI","CL","CM","CN","CO","CR","CV","CW","CY","CZ","DE","DJ","DK","DM","DO","DZ","EC","EE","EG","ES","ET","FI","FJ","FO","FR","GA","GB","GD","GE","GF","GG","GH","GI","GM","GN","GP","GR","GT","GU","GY","HK","HN","HR","HT","HU","ID","IE","IL","IM","IN","IQ","IS","IT","JE","JM","JO","KE","KG","KH","KR","KW","KY","KZ","LA","LB","LC","LI","LK","LS","LT","LU","LV","LY","MA","MC","ME","MG","MK","ML","MM","MN","MO","MQ","MR","MT","MU","MV","MW","MX","MY","MZ","NA","NC","NE","NG","NI","NL","NO","NP","NZ","OM","PA","PE","PF","PG","PH","PK","PL","PR","PS","PT","PY","QA","RE","RO","RS","RW","SA","SC","SD","SE","SG","SI","SK","SL","SN","SO","SR","SV","SZ","TG","TH","TN","TO","TR","TT","TW","UG","US","UY","UZ","VC","VI","VN","YE","ZA","ZM","ZW"],"creativeSets":[{"creativeSetId":"9d234c91-dcb2-4533-9fc4-2a06e35c963b","perDay":20,"perMonth":0,"perWeek":0,"totalMax":20,"value":"0","creatives":[{"creativeInstanceId":"f445f89f-0d2c-4b55-9a65-25c5f8757ca1","targetUrl":"https://brave.com/podcast/e100/?mtm_source=brave-browser&mtm_medium=brave-ntp&mtm_campaign=brave-technologist&mtm_content=podcast","alt":"Zcash and the Fight for Privacy in the Digital Age with Arjun Khemani","companyName":"The Brave Technologist Podcast: Episode 100","wallpaper":{"type":"image","relativeUrl":"01d06365-7098-4e93-91cf-b7970bea4f67/e395a2d8-e099-4626-b493-a024f2865f3f.jpg","button":{"image":{"relativeUrl":"01d06365-7098-4e93-91cf-b7970bea4f67/095da34e-6529-4bd0-a14e-3d592b6d0728.png"}},"focalPoint":{"x":1250,"y":720}}},{"creativeInstanceId":"ca60442c-ca78-4b7d-89e1-b25789868e1f","targetUrl":"https://brave.com/podcast/e100/?mtm_source=brave-browser&mtm_medium=brave-ntp&mtm_campaign=brave-technologist&mtm_content=podcast","alt":"Zcash and the Fight for Privacy in the Digital Age with Arjun Khemani","companyName":"The Brave Technologist Podcast: Episode 100","wallpaper":{"type":"image","relativeUrl":"60ed9071-7e06-4b20-97d3-ee56f791dbed/84288a26-3628-43da-9c63-9f2181074721.jpg","button":{"image":{"relativeUrl":"60ed9071-7e06-4b20-97d3-ee56f791dbed/095da34e-6529-4bd0-a14e-3d592b6d0728.png"}},"focalPoint":{"x":1280,"y":720}}}]}]}]}